twilight_log_parser/__init__.py
twilight_log_parser/constants.py
twilight_log_parser/ingest_log.py
twilight_log_parser/log_parser.py
twilight_log_parser/py.typed
twilight_log_parser/core/__init__.py
twilight_log_parser/core/board.py
twilight_log_parser/core/card.py
twilight_log_parser/core/country.py
twilight_log_parser/core/game.py
twilight_log_parser/core/play.py
twilight_log_parser/data/cards.csv
twilight_log_parser/data/countries.csv
twilight_log_parser/line_handlers/__init__.py
twilight_log_parser/line_handlers/actions.py
twilight_log_parser/line_handlers/base.py
twilight_log_parser/line_handlers/board_state.py
twilight_log_parser/line_handlers/deck_state.py
twilight_log_parser/line_handlers/game_setup.py
twilight_log_parser/line_handlers/scoring.py
twilight_log_parser/line_handlers/special.py
twilight_log_parser/utils/__init__.py
twilight_log_parser/utils/card_state.py
twilight_log_parser/utils/helpers.py
twilight_log_parser-0.1.4.dist-info/METADATA
twilight_log_parser-0.1.4.dist-info/WHEEL
twilight_log_parser-0.1.4.dist-info/licenses/LICENSE
twilight_log_parser-0.1.4.dist-info/RECORD
