Metadata-Version: 2.4
Name: twilight-log-parser
Version: 0.1.4
Summary: API to parse Twilight Struggle game logs into a structured format.
Project-URL: Homepage, https://github.com/browning-gentry/twilight-log-parser
Project-URL: Bug Tracker, https://github.com/browning-gentry/twilight-log-parser/issues
Author: Browning Gentry
License:   GNU GENERAL PUBLIC LICENSE
License-File: LICENSE
Classifier: Operating System :: OS Independent
Classifier: Programming Language :: Python :: 3
Requires-Python: >=3.9.6
Requires-Dist: frozendict>=2.4.6
Requires-Dist: typing-extensions==4.12.2
Provides-Extra: dev
Requires-Dist: black>=24.10.0; extra == 'dev'
Requires-Dist: flake8-pyproject>=1.2.3; extra == 'dev'
Requires-Dist: flake8>=7.1.1; extra == 'dev'
Requires-Dist: isort>=5.13.2; extra == 'dev'
Requires-Dist: pre-commit>=4.1.0; extra == 'dev'
